coherence_ua/__init__.py
coherence_ua/transformer_coherence.py
coherence_ua/models/ukrainian-iu-ud-2.3-181115.udpipe
coherence_ua/models/utils.py
coherence_ua/models/vocab.subwords
coherence_ua/models/weights/chk-2-0.0917-0.8678.data-00000-of-00002
coherence_ua/models/weights/chk-2-0.0917-0.8678.data-00001-of-00002
coherence_ua/models/weights/chk-2-0.0917-0.8678.index
coherence_ua-0.0.4.dist-info/LICENSE
coherence_ua-0.0.4.dist-info/METADATA
coherence_ua-0.0.4.dist-info/WHEEL
coherence_ua-0.0.4.dist-info/top_level.txt
coherence_ua-0.0.4.dist-info/RECORD
