Metadata-Version: 2.1
Name: coherence-ua
Version: 0.0.4
Summary: Transformer-based model to estimate the coherence of Ukrainian-language texts
Home-page: https://github.com/artemkramov/coherence-ua
Author: Artem Kramov
Author-email: artemkramov@gmail.com
License: UNKNOWN
Platform: UNKNOWN
Requires-Dist: ufal.udpipe
Requires-Dist: tensorflow
Requires-Dist: tensorflow-datasets
Requires-Dist: numpy
